dtwalign/__init__.py
dtwalign/backtrack.py
dtwalign/cost.py
dtwalign/distance.py
dtwalign/dtw.py
dtwalign/result.py
dtwalign/step_pattern.py
dtwalign/window.py
dtwalign-0.1.1.dist-info/LICENSE.txt
dtwalign-0.1.1.dist-info/METADATA
dtwalign-0.1.1.dist-info/WHEEL
dtwalign-0.1.1.dist-info/top_level.txt
dtwalign-0.1.1.dist-info/RECORD
