Metadata-Version: 2.1
Name: dtwalign
Version: 0.1.1
Summary: Comprehensive DTW package which enables partial mathing and has various constraint options
Home-page: https://github.com/statefb/dtwalign
Author: Takehiro Suzuki
Author-email: 
License: MIT
Classifier: Programming Language :: Python :: 3.5
Classifier: Programming Language :: Python :: 3.6
Classifier: Topic :: Scientific/Engineering
License-File: LICENSE.txt
Requires-Dist: numpy
Requires-Dist: matplotlib
Requires-Dist: seaborn (>=0.8.1)
Requires-Dist: networkx
Requires-Dist: numba (>=0.34.0)
Requires-Dist: scipy
